{
  "lesson_id": "bt_lesson_01",
  "lesson_name": "BT Core Patterns",
  "domain": "behavior_tree",
  "model": "models/bt-lora-v2/final",
  "base_model": "meta-llama/Meta-Llama-3.1-70B",
  "timestamp": "20260307_230901",
  "total_prompts": 20,
  "valid_syntax": 19,
  "valid_syntax_pct": 95.0,
  "avg_similarity_score": 95.5,
  "timeout_count": 0,
  "per_category": {
    "simple_sequence": {
      "count": 2,
      "valid": 1,
      "avg_score": 92.8
    },
    "selector": {
      "count": 1,
      "valid": 1,
      "avg_score": 100.0
    },
    "blackboard_decorator": {
      "count": 1,
      "valid": 1,
      "avg_score": 100.0
    },
    "patrol": {
      "count": 1,
      "valid": 1,
      "avg_score": 100.0
    },
    "chase_patrol": {
      "count": 1,
      "valid": 1,
      "avg_score": 100.0
    },
    "service": {
      "count": 1,
      "valid": 1,
      "avg_score": 100.0
    },
    "cooldown": {
      "count": 1,
      "valid": 1,
      "avg_score": 100.0
    },
    "timelimit": {
      "count": 1,
      "valid": 1,
      "avg_score": 100.0
    },
    "force_success": {
      "count": 1,
      "valid": 1,
      "avg_score": 100.0
    },
    "multi_key": {
      "count": 1,
      "valid": 1,
      "avg_score": 100.0
    },
    "rotate_face": {
      "count": 1,
      "valid": 1,
      "avg_score": 85.7
    },
    "three_branch_selector": {
      "count": 1,
      "valid": 1,
      "avg_score": 93.8
    },
    "wait_blackboard": {
      "count": 1,
      "valid": 1,
      "avg_score": 100.0
    },
    "focus_service": {
      "count": 1,
      "valid": 1,
      "avg_score": 100.0
    },
    "destroy_task": {
      "count": 1,
      "valid": 1,
      "avg_score": 100.0
    },
    "set_blackboard": {
      "count": 1,
      "valid": 1,
      "avg_score": 100.0
    },
    "nested_selector": {
      "count": 1,
      "valid": 1,
      "avg_score": 95.0
    },
    "finish_result": {
      "count": 1,
      "valid": 1,
      "avg_score": 66.7
    },
    "multi_service": {
      "count": 1,
      "valid": 1,
      "avg_score": 83.3
    }
  }
}